projectpythonnew/__init__.py
projectpythonnew/projectpackage/__init__.py
projectpythonnew/projectpackage/alien.py
projectpythonnew/projectpackage/alien_invasion.py
projectpythonnew/projectpackage/bullet.py
projectpythonnew/projectpackage/button.py
projectpythonnew/projectpackage/game_stats.py
projectpythonnew/projectpackage/scoreboard.py
projectpythonnew/projectpackage/settings.py
projectpythonnew/projectpackage/ship.py
machinestatusnew-0.1.dist-info/METADATA
machinestatusnew-0.1.dist-info/WHEEL
machinestatusnew-0.1.dist-info/top_level.txt
machinestatusnew-0.1.dist-info/RECORD
